odoo/addons/stock_quant_reservation_info_mrp/README.rst
odoo/addons/stock_quant_reservation_info_mrp/__init__.py
odoo/addons/stock_quant_reservation_info_mrp/__manifest__.py
odoo/addons/stock_quant_reservation_info_mrp/i18n/stock_quant_reservation_info_mrp.pot
odoo/addons/stock_quant_reservation_info_mrp/models/__init__.py
odoo/addons/stock_quant_reservation_info_mrp/models/stock_move_line.py
odoo/addons/stock_quant_reservation_info_mrp/readme/CONTRIBUTORS.rst
odoo/addons/stock_quant_reservation_info_mrp/readme/DESCRIPTION.rst
odoo/addons/stock_quant_reservation_info_mrp/readme/USAGE.rst
odoo/addons/stock_quant_reservation_info_mrp/static/description/icon.png
odoo/addons/stock_quant_reservation_info_mrp/static/description/index.html
odoo/addons/stock_quant_reservation_info_mrp/views/stock_move_line.xml
odoo14_addon_stock_quant_reservation_info_mrp-14.0.1.1.1.dist-info/METADATA
odoo14_addon_stock_quant_reservation_info_mrp-14.0.1.1.1.dist-info/WHEEL
odoo14_addon_stock_quant_reservation_info_mrp-14.0.1.1.1.dist-info/top_level.txt
odoo14_addon_stock_quant_reservation_info_mrp-14.0.1.1.1.dist-info/RECORD
